NiukeWangMingqiChunzhaoShixiBeizhanGonglveJishuPian2019/README.md
NiukeWangMingqiChunzhaoShixiBeizhanGonglveJishuPian2019/__init__.py
NiukeWangMingqiChunzhaoShixiBeizhanGonglveJishuPian2019/__main__.py
NiukeWangMingqiChunzhaoShixiBeizhanGonglveJishuPian2019/file.pdf
NiukeWangMingqiChunzhaoShixiBeizhanGonglveJishuPian2019/index.html
niuke_wang_mingqi_chunzhao_shixi_beizhan_gonglve_jishu_pian_2019-2024.3.4.0.dist-info/METADATA
niuke_wang_mingqi_chunzhao_shixi_beizhan_gonglve_jishu_pian_2019-2024.3.4.0.dist-info/WHEEL
niuke_wang_mingqi_chunzhao_shixi_beizhan_gonglve_jishu_pian_2019-2024.3.4.0.dist-info/entry_points.txt
niuke_wang_mingqi_chunzhao_shixi_beizhan_gonglve_jishu_pian_2019-2024.3.4.0.dist-info/top_level.txt
niuke_wang_mingqi_chunzhao_shixi_beizhan_gonglve_jishu_pian_2019-2024.3.4.0.dist-info/RECORD
